.gitignore
Beantop.e4p
LICENSE.txt
README.md
setpath.sh
setup.cfg
setup.py
beantop/__init__.py
beantop/arguments.py
beantop/beanstalkd.py
beantop/beanstalkdstats.py
beantop/beantop.py
beantop/charreader.py
beantop/clock.py
beantop/console.py
beantop/factory.py
beantop/screenprinter.py
beantop.egg-info/PKG-INFO
beantop.egg-info/SOURCES.txt
beantop.egg-info/dependency_links.txt
beantop.egg-info/entry_points.txt
beantop.egg-info/requires.txt
beantop.egg-info/top_level.txt
beantop/test/coverage.sh
beantop/test/lint.sh
beantop/test/mocks.py
beantop/test/pylint.config
beantop/test/runtests.sh
beantop/test/test_arguments.py
beantop/test/test_beanstalkd.py
beantop/test/test_beanstalkdstats.py
beantop/test/test_charreader.py
beantop/test/test_clock.py
beantop/test/test_console.py
beantop/test/test_factory.py
beantop/test/test_integration.py
beantop/test/test_screenprinter.py
scripts/beantop