Metadata-Version: 1.1
Name: beantop
Version: 0.2.5
Summary: UNKNOWN
Home-page: https://github.com/alexsiri7/beantop
Author: alexsiri7
Author-email: alexsiri7@gmail.com
License: GPL
Platform: UNKNOWN
Classifier: Development Status :: 4 - Beta
Classifier: Environment :: Console
Classifier: Programming Language :: Python
Classifier: Intended Audience :: System Administrators
Classifier: Topic :: Utilities
